odoo/addons/account_analytic_report/CHANGELOG.md
odoo/addons/account_analytic_report/README.rst
odoo/addons/account_analytic_report/__init__.py
odoo/addons/account_analytic_report/__manifest__.py
odoo/addons/account_analytic_report/i18n/account_analytic_report.pot
odoo/addons/account_analytic_report/i18n/es.po
odoo/addons/account_analytic_report/i18n/es_CA.po
odoo/addons/account_analytic_report/models/__init__.py
odoo/addons/account_analytic_report/models/analytic_line.py
odoo/addons/account_analytic_report/models/ir_actions_report.py
odoo/addons/account_analytic_report/reports/__init__.py
odoo/addons/account_analytic_report/reports/abstract_report.py
odoo/addons/account_analytic_report/reports/abstract_report_xlsx.py
odoo/addons/account_analytic_report/reports/analytic_multilevel.py
odoo/addons/account_analytic_report/reports/analytic_multilevel_xlsx.py
odoo/addons/account_analytic_report/reports/commons.py
odoo/addons/account_analytic_report/reports/templates/analytic_multilevel.xml
odoo/addons/account_analytic_report/reports/templates/layouts.xml
odoo/addons/account_analytic_report/security/ir.model.access.csv
odoo/addons/account_analytic_report/security/security.xml
odoo/addons/account_analytic_report/static/description/icon.png
odoo/addons/account_analytic_report/static/src/css/main.css
odoo/addons/account_analytic_report/static/src/css/report.css
odoo/addons/account_analytic_report/static/src/css/report_html.css
odoo/addons/account_analytic_report/static/src/js/report.esm.js
odoo/addons/account_analytic_report/static/src/js/report_action.esm.js
odoo/addons/account_analytic_report/static/src/xml/report.xml
odoo/addons/account_analytic_report/views/menuitems.xml
odoo/addons/account_analytic_report/views/reports.xml
odoo/addons/account_analytic_report/wizards/__init__.py
odoo/addons/account_analytic_report/wizards/abstract_wizard.py
odoo/addons/account_analytic_report/wizards/analytic_multilevel_report_wizard.py
odoo_addon_account_analytic_report-16.0.1.0.1.dist-info/METADATA
odoo_addon_account_analytic_report-16.0.1.0.1.dist-info/WHEEL
odoo_addon_account_analytic_report-16.0.1.0.1.dist-info/top_level.txt
odoo_addon_account_analytic_report-16.0.1.0.1.dist-info/RECORD
