Metadata-Version: 2.1
Name: odoo-addon-account-analytic-report
Version: 16.0.1.0.1
Summary: Account Analytic Multilevel Reports
Home-page: https://somit.coop
Author: Som It Cooperatiu SCCL
License: AGPL-3
Classifier: Programming Language :: Python
Classifier: Framework :: Odoo
Classifier: Framework :: Odoo :: 16.0
Classifier: License :: OSI Approved :: GNU Affero General Public License v3
Requires-Python: >=3.10
Requires-Dist: odoo-addon-account-analytic-parent<16.1dev,>=16.0dev
Requires-Dist: odoo-addon-report-xlsx<16.1dev,>=16.0dev
Requires-Dist: odoo<16.1dev,>=16.0a
